<chunk name="Object" index="0">
  <items count="2">
    <item name="GUID" type_name="gh_guid" type_code="9">5db0fb89-4f22-4f09-a777-fa5e55aed7ec</item>
    <item name="Name" type_name="gh_string" type_code="10">Equality</item>
  </items>
  <chunks count="1">
    <chunk name="Container">
      <items count="4">
        <item name="Description" type_name="gh_string" type_code="10">Test for (in)equality of two numbers</item>
        <item name="InstanceGuid" type_name="gh_guid" type_code="9">16d66763-e4c4-4c6a-bc54-ecb4b92f6db8</item>
        <item name="Name" type_name="gh_string" type_code="10">Equality</item>
        <item name="NickName" type_name="gh_string" type_code="10">Equals</item>
      </items>
      <chunks count="5">
        <chunk name="Attributes">
          <items count="2">
            <item name="Bounds" type_name="gh_drawing_rectanglef" type_code="35">
              <X>8910</X>
              <Y>-3618</Y>
              <W>66</W>
              <H>55</H>
            </item>
            <item name="Pivot" type_name="gh_drawing_pointf" type_code="31">
              <X>8941</X>
              <Y>-3590</Y>
            </item>
          </items>
        </chunk>
        <chunk name="param_input" index="0">
          <items count="7">
            <item name="Description" type_name="gh_string" type_code="10">Number to compare</item>
            <item name="InstanceGuid" type_name="gh_guid" type_code="9">0cc24c01-946f-48f5-b078-84ef564887d0</item>
            <item name="Name" type_name="gh_string" type_code="10">First Number</item>
            <item name="NickName" type_name="gh_string" type_code="10">A</item>
            <item name="Optional" type_name="gh_bool" type_code="1">false</item>
            <item name="Source" index="0" type_name="gh_guid" type_code="9">22ef6e51-2e53-4d95-a428-74416923e78f</item>
            <item name="SourceCount" type_name="gh_int32" type_code="3">1</item>
          </items>
          <chunks count="1">
            <chunk name="Attributes">
              <items count="2">
                <item name="Bounds" type_name="gh_drawing_rectanglef" type_code="35">
                  <X>8912</X>
                  <Y>-3616</Y>
                  <W>14</W>
                  <H>25</H>
                </item>
                <item name="Pivot" type_name="gh_drawing_pointf" type_code="31">
                  <X>8920.5</X>
                  <Y>-3603.25</Y>
                </item>
              </items>
            </chunk>
          </chunks>
        </chunk>
        <chunk name="param_input" index="1">
          <items count="7">
            <item name="Description" type_name="gh_string" type_code="10">Number to compare to</item>
            <item name="InstanceGuid" type_name="gh_guid" type_code="9">efa539fa-6d65-4e95-906b-360dcdcf1c38</item>
            <item name="Name" type_name="gh_string" type_code="10">Second Number</item>
            <item name="NickName" type_name="gh_string" type_code="10">B</item>
            <item name="Optional" type_name="gh_bool" type_code="1">false</item>
            <item name="Source" index="0" type_name="gh_guid" type_code="9">bb02cfb4-2f9c-4a95-a532-45b7cc5fa3cc</item>
            <item name="SourceCount" type_name="gh_int32" type_code="3">1</item>
          </items>
          <chunks count="1">
            <chunk name="Attributes">
              <items count="2">
                <item name="Bounds" type_name="gh_drawing_rectanglef" type_code="35">
                  <X>8912</X>
                  <Y>-3591</Y>
                  <W>14</W>
                  <H>26</H>
                </item>
                <item name="Pivot" type_name="gh_drawing_pointf" type_code="31">
                  <X>8920.5</X>
                  <Y>-3577.75</Y>
                </item>
              </items>
            </chunk>
          </chunks>
        </chunk>
        <chunk name="param_output" index="0">
          <items count="6">
            <item name="Description" type_name="gh_string" type_code="10">True if A = B</item>
            <item name="InstanceGuid" type_name="gh_guid" type_code="9">19966a7d-1f97-4b0c-8e22-2656d92a47ac</item>
            <item name="Name" type_name="gh_string" type_code="10">Equality</item>
            <item name="NickName" type_name="gh_string" type_code="10">=</item>
            <item name="Optional" type_name="gh_bool" type_code="1">false</item>
            <item name="SourceCount" type_name="gh_int32" type_code="3">0</item>
          </items>
          <chunks count="1">
            <chunk name="Attributes">
              <items count="2">
                <item name="Bounds" type_name="gh_drawing_rectanglef" type_code="35">
                  <X>8956</X>
                  <Y>-3616</Y>
                  <W>18</W>
                  <H>25</H>
                </item>
                <item name="Pivot" type_name="gh_drawing_pointf" type_code="31">
                  <X>8965</X>
                  <Y>-3603.25</Y>
                </item>
              </items>
            </chunk>
          </chunks>
        </chunk>
        <chunk name="param_output" index="1">
          <items count="6">
            <item name="Description" type_name="gh_string" type_code="10">True if A ≠ B</item>
            <item name="InstanceGuid" type_name="gh_guid" type_code="9">7d2de1da-f3b6-4855-88e8-f50c28f37e47</item>
            <item name="Name" type_name="gh_string" type_code="10">Inequality</item>
            <item name="NickName" type_name="gh_string" type_code="10">≠</item>
            <item name="Optional" type_name="gh_bool" type_code="1">false</item>
            <item name="SourceCount" type_name="gh_int32" type_code="3">0</item>
          </items>
          <chunks count="1">
            <chunk name="Attributes">
              <items count="2">
                <item name="Bounds" type_name="gh_drawing_rectanglef" type_code="35">
                  <X>8956</X>
                  <Y>-3591</Y>
                  <W>18</W>
                  <H>26</H>
                </item>
                <item name="Pivot" type_name="gh_drawing_pointf" type_code="31">
                  <X>8965</X>
                  <Y>-3577.75</Y>
                </item>
              </items>
            </chunk>
          </chunks>
        </chunk>
      </chunks>
    </chunk>
  </chunks>
</chunk>