<chunk name="Object" index="0">
  <items count="2">
    <item name="GUID" type_name="gh_guid" type_code="9">afb96615-c59a-45c9-9cac-e27acb1c7ca0</item>
    <item name="Name" type_name="gh_string" type_code="10">Explode</item>
  </items>
  <chunks count="1">
    <chunk name="Container">
      <items count="5">
        <item name="Description" type_name="gh_string" type_code="10">Explode a curve into smaller segments.</item>
        <item name="Hidden" type_name="gh_bool" type_code="1">true</item>
        <item name="InstanceGuid" type_name="gh_guid" type_code="9">28ca5c61-22ca-4ff6-9db0-571edccdfa5a</item>
        <item name="Name" type_name="gh_string" type_code="10">Explode</item>
        <item name="NickName" type_name="gh_string" type_code="10">Explode</item>
      </items>
      <chunks count="5">
        <chunk name="Attributes">
          <items count="2">
            <item name="Bounds" type_name="gh_drawing_rectanglef" type_code="35">
              <X>8058</X>
              <Y>-3671</Y>
              <W>65</W>
              <H>66</H>
            </item>
            <item name="Pivot" type_name="gh_drawing_pointf" type_code="31">
              <X>8089</X>
              <Y>-3638</Y>
            </item>
          </items>
        </chunk>
        <chunk name="param_input" index="0">
          <items count="7">
            <item name="Description" type_name="gh_string" type_code="10">Curve to explode</item>
            <item name="InstanceGuid" type_name="gh_guid" type_code="9">cf43fa20-105e-4ded-b5e8-7328f4f65942</item>
            <item name="Name" type_name="gh_string" type_code="10">Curve</item>
            <item name="NickName" type_name="gh_string" type_code="10">C</item>
            <item name="Optional" type_name="gh_bool" type_code="1">false</item>
            <item name="Source" index="0" type_name="gh_guid" type_code="9">118b2ec5-e207-4267-a909-8bebe92b571c</item>
            <item name="SourceCount" type_name="gh_int32" type_code="3">1</item>
          </items>
          <chunks count="1">
            <chunk name="Attributes">
              <items count="2">
                <item name="Bounds" type_name="gh_drawing_rectanglef" type_code="35">
                  <X>8060</X>
                  <Y>-3669</Y>
                  <W>14</W>
                  <H>31</H>
                </item>
                <item name="Pivot" type_name="gh_drawing_pointf" type_code="31">
                  <X>8068.5</X>
                  <Y>-3653.5</Y>
                </item>
              </items>
            </chunk>
          </chunks>
        </chunk>
        <chunk name="param_input" index="1">
          <items count="6">
            <item name="Description" type_name="gh_string" type_code="10">Recursive decomposition until all segments are atomic</item>
            <item name="InstanceGuid" type_name="gh_guid" type_code="9">ce7f8097-c11d-4a3f-83df-39b549e4971c</item>
            <item name="Name" type_name="gh_string" type_code="10">Recursive</item>
            <item name="NickName" type_name="gh_string" type_code="10">R</item>
            <item name="Optional" type_name="gh_bool" type_code="1">false</item>
            <item name="SourceCount" type_name="gh_int32" type_code="3">0</item>
          </items>
          <chunks count="2">
            <chunk name="Attributes">
              <items count="2">
                <item name="Bounds" type_name="gh_drawing_rectanglef" type_code="35">
                  <X>8060</X>
                  <Y>-3638</Y>
                  <W>14</W>
                  <H>31</H>
                </item>
                <item name="Pivot" type_name="gh_drawing_pointf" type_code="31">
                  <X>8068.5</X>
                  <Y>-3622.5</Y>
                </item>
              </items>
            </chunk>
            <chunk name="PersistentData">
              <items count="1">
                <item name="Count" type_name="gh_int32" type_code="3">1</item>
              </items>
              <chunks count="1">
                <chunk name="Branch" index="0">
                  <items count="2">
                    <item name="Count" type_name="gh_int32" type_code="3">1</item>
                    <item name="Path" type_name="gh_string" type_code="10">{0}</item>
                  </items>
                  <chunks count="1">
                    <chunk name="Item" index="0">
                      <items count="1">
                        <item name="boolean" type_name="gh_bool" type_code="1">true</item>
                      </items>
                    </chunk>
                  </chunks>
                </chunk>
              </chunks>
            </chunk>
          </chunks>
        </chunk>
        <chunk name="param_output" index="0">
          <items count="7">
            <item name="Access" type_name="gh_int32" type_code="3">1</item>
            <item name="Description" type_name="gh_string" type_code="10">Exploded segments that make up the base curve</item>
            <item name="InstanceGuid" type_name="gh_guid" type_code="9">22a85713-a3cd-4242-9094-2c82698db63b</item>
            <item name="Name" type_name="gh_string" type_code="10">Segments</item>
            <item name="NickName" type_name="gh_string" type_code="10">S</item>
            <item name="Optional" type_name="gh_bool" type_code="1">false</item>
            <item name="SourceCount" type_name="gh_int32" type_code="3">0</item>
          </items>
          <chunks count="1">
            <chunk name="Attributes">
              <items count="2">
                <item name="Bounds" type_name="gh_drawing_rectanglef" type_code="35">
                  <X>8104</X>
                  <Y>-3669</Y>
                  <W>17</W>
                  <H>31</H>
                </item>
                <item name="Pivot" type_name="gh_drawing_pointf" type_code="31">
                  <X>8112.5</X>
                  <Y>-3653.5</Y>
                </item>
              </items>
            </chunk>
          </chunks>
        </chunk>
        <chunk name="param_output" index="1">
          <items count="7">
            <item name="Access" type_name="gh_int32" type_code="3">1</item>
            <item name="Description" type_name="gh_string" type_code="10">Vertices of the exploded segments</item>
            <item name="InstanceGuid" type_name="gh_guid" type_code="9">2616d13b-932d-4e68-9b69-aeca48508b52</item>
            <item name="Name" type_name="gh_string" type_code="10">Vertices</item>
            <item name="NickName" type_name="gh_string" type_code="10">V</item>
            <item name="Optional" type_name="gh_bool" type_code="1">false</item>
            <item name="SourceCount" type_name="gh_int32" type_code="3">0</item>
          </items>
          <chunks count="1">
            <chunk name="Attributes">
              <items count="2">
                <item name="Bounds" type_name="gh_drawing_rectanglef" type_code="35">
                  <X>8104</X>
                  <Y>-3638</Y>
                  <W>17</W>
                  <H>31</H>
                </item>
                <item name="Pivot" type_name="gh_drawing_pointf" type_code="31">
                  <X>8112.5</X>
                  <Y>-3622.5</Y>
                </item>
              </items>
            </chunk>
          </chunks>
        </chunk>
      </chunks>
    </chunk>
  </chunks>
</chunk>