<chunk name="Object" index="0">
  <items count="2">
    <item name="GUID" type_name="gh_guid" type_code="9">1274d51a-81e6-4ccf-ad1f-0edf4c769cac</item>
    <item name="Name" type_name="gh_string" type_code="10">Text Join</item>
  </items>
  <chunks count="1">
    <chunk name="Container">
      <items count="5">
        <item name="Description" type_name="gh_string" type_code="10">Join a collection of text fragments into one</item>
        <item name="Hidden" type_name="gh_bool" type_code="1">true</item>
        <item name="InstanceGuid" type_name="gh_guid" type_code="9">5d95de33-d26d-498b-b18a-2c2ec3e5cf40</item>
        <item name="Name" type_name="gh_string" type_code="10">Text Join</item>
        <item name="NickName" type_name="gh_string" type_code="10">Join</item>
      </items>
      <chunks count="4">
        <chunk name="Attributes">
          <items count="2">
            <item name="Bounds" type_name="gh_drawing_rectanglef" type_code="35">
              <X>19074</X>
              <Y>2087</Y>
              <W>64</W>
              <H>44</H>
            </item>
            <item name="Pivot" type_name="gh_drawing_pointf" type_code="31">
              <X>19104</X>
              <Y>2109</Y>
            </item>
          </items>
        </chunk>
        <chunk name="param_input" index="0">
          <items count="8">
            <item name="Access" type_name="gh_int32" type_code="3">1</item>
            <item name="Description" type_name="gh_string" type_code="10">Text fragments to join.</item>
            <item name="InstanceGuid" type_name="gh_guid" type_code="9">5366f568-7484-47ec-aa18-9045159c17c1</item>
            <item name="Name" type_name="gh_string" type_code="10">Text</item>
            <item name="NickName" type_name="gh_string" type_code="10">T</item>
            <item name="Optional" type_name="gh_bool" type_code="1">false</item>
            <item name="Source" index="0" type_name="gh_guid" type_code="9">c78abd03-fb49-4574-96e7-3d6a84a1369a</item>
            <item name="SourceCount" type_name="gh_int32" type_code="3">1</item>
          </items>
          <chunks count="1">
            <chunk name="Attributes">
              <items count="2">
                <item name="Bounds" type_name="gh_drawing_rectanglef" type_code="35">
                  <X>19076</X>
                  <Y>2089</Y>
                  <W>13</W>
                  <H>20</H>
                </item>
                <item name="Pivot" type_name="gh_drawing_pointf" type_code="31">
                  <X>19084</X>
                  <Y>2099</Y>
                </item>
              </items>
            </chunk>
          </chunks>
        </chunk>
        <chunk name="param_input" index="1">
          <items count="6">
            <item name="Description" type_name="gh_string" type_code="10">Fragment separator.</item>
            <item name="InstanceGuid" type_name="gh_guid" type_code="9">661ee58d-6f81-4551-875c-69b0ae4710a7</item>
            <item name="Name" type_name="gh_string" type_code="10">Join</item>
            <item name="NickName" type_name="gh_string" type_code="10">J</item>
            <item name="Optional" type_name="gh_bool" type_code="1">true</item>
            <item name="SourceCount" type_name="gh_int32" type_code="3">0</item>
          </items>
          <chunks count="2">
            <chunk name="Attributes">
              <items count="2">
                <item name="Bounds" type_name="gh_drawing_rectanglef" type_code="35">
                  <X>19076</X>
                  <Y>2109</Y>
                  <W>13</W>
                  <H>20</H>
                </item>
                <item name="Pivot" type_name="gh_drawing_pointf" type_code="31">
                  <X>19084</X>
                  <Y>2119</Y>
                </item>
              </items>
            </chunk>
            <chunk name="PersistentData">
              <items count="1">
                <item name="Count" type_name="gh_int32" type_code="3">1</item>
              </items>
              <chunks count="1">
                <chunk name="Branch" index="0">
                  <items count="2">
                    <item name="Count" type_name="gh_int32" type_code="3">1</item>
                    <item name="Path" type_name="gh_string" type_code="10">{0}</item>
                  </items>
                  <chunks count="1">
                    <chunk name="Item" index="0">
                      <items count="2">
                        <item name="null_string" type_name="gh_bool" type_code="1">false</item>
                        <item name="string" type_name="gh_string" type_code="10">,</item>
                      </items>
                    </chunk>
                  </chunks>
                </chunk>
              </chunks>
            </chunk>
          </chunks>
        </chunk>
        <chunk name="param_output" index="0">
          <items count="6">
            <item name="Description" type_name="gh_string" type_code="10">Resulting text</item>
            <item name="InstanceGuid" type_name="gh_guid" type_code="9">ba47db07-2479-44bd-86f3-3416c91be87f</item>
            <item name="Name" type_name="gh_string" type_code="10">Result</item>
            <item name="NickName" type_name="gh_string" type_code="10">R</item>
            <item name="Optional" type_name="gh_bool" type_code="1">false</item>
            <item name="SourceCount" type_name="gh_int32" type_code="3">0</item>
          </items>
          <chunks count="1">
            <chunk name="Attributes">
              <items count="2">
                <item name="Bounds" type_name="gh_drawing_rectanglef" type_code="35">
                  <X>19119</X>
                  <Y>2089</Y>
                  <W>17</W>
                  <H>40</H>
                </item>
                <item name="Pivot" type_name="gh_drawing_pointf" type_code="31">
                  <X>19127.5</X>
                  <Y>2109</Y>
                </item>
              </items>
            </chunk>
          </chunks>
        </chunk>
      </chunks>
    </chunk>
  </chunks>
</chunk>