<chunk name="Object" index="0">
  <items count="2">
    <item name="GUID" type_name="gh_guid" type_code="9">3581f42a-9592-4549-bd6b-1c0fc39d067b</item>
    <item name="Name" type_name="gh_string" type_code="10">Construct Point</item>
  </items>
  <chunks count="1">
    <chunk name="Container">
      <items count="5">
        <item name="Description" type_name="gh_string" type_code="10">Construct a point from {xyz} coordinates.</item>
        <item name="Hidden" type_name="gh_bool" type_code="1">true</item>
        <item name="InstanceGuid" type_name="gh_guid" type_code="9">b480285f-f483-4ba5-af44-cb4c6b4068c9</item>
        <item name="Name" type_name="gh_string" type_code="10">Construct Point</item>
        <item name="NickName" type_name="gh_string" type_code="10">Pt</item>
      </items>
      <chunks count="5">
        <chunk name="Attributes">
          <items count="2">
            <item name="Bounds" type_name="gh_drawing_rectanglef" type_code="35">
              <X>12913</X>
              <Y>3970</Y>
              <W>68</W>
              <H>64</H>
            </item>
            <item name="Pivot" type_name="gh_drawing_pointf" type_code="31">
              <X>12944</X>
              <Y>4002</Y>
            </item>
          </items>
        </chunk>
        <chunk name="param_input" index="0">
          <items count="7">
            <item name="Description" type_name="gh_string" type_code="10">{x} coordinate</item>
            <item name="InstanceGuid" type_name="gh_guid" type_code="9">92a7e4f7-6c80-4469-bff9-8d2f87868a5a</item>
            <item name="Name" type_name="gh_string" type_code="10">X coordinate</item>
            <item name="NickName" type_name="gh_string" type_code="10">X</item>
            <item name="Optional" type_name="gh_bool" type_code="1">false</item>
            <item name="Source" index="0" type_name="gh_guid" type_code="9">6c8e72c4-c7aa-4815-9fc5-794680ab5531</item>
            <item name="SourceCount" type_name="gh_int32" type_code="3">1</item>
          </items>
          <chunks count="2">
            <chunk name="Attributes">
              <items count="2">
                <item name="Bounds" type_name="gh_drawing_rectanglef" type_code="35">
                  <X>12915</X>
                  <Y>3972</Y>
                  <W>14</W>
                  <H>20</H>
                </item>
                <item name="Pivot" type_name="gh_drawing_pointf" type_code="31">
                  <X>12923.5</X>
                  <Y>3982</Y>
                </item>
              </items>
            </chunk>
            <chunk name="PersistentData">
              <items count="1">
                <item name="Count" type_name="gh_int32" type_code="3">1</item>
              </items>
              <chunks count="1">
                <chunk name="Branch" index="0">
                  <items count="2">
                    <item name="Count" type_name="gh_int32" type_code="3">1</item>
                    <item name="Path" type_name="gh_string" type_code="10">{0}</item>
                  </items>
                  <chunks count="1">
                    <chunk name="Item" index="0">
                      <items count="1">
                        <item name="number" type_name="gh_double" type_code="6">0</item>
                      </items>
                    </chunk>
                  </chunks>
                </chunk>
              </chunks>
            </chunk>
          </chunks>
        </chunk>
        <chunk name="param_input" index="1">
          <items count="7">
            <item name="Description" type_name="gh_string" type_code="10">{y} coordinate</item>
            <item name="InstanceGuid" type_name="gh_guid" type_code="9">8d795277-89fb-4fa0-84cd-8363774f2a33</item>
            <item name="Name" type_name="gh_string" type_code="10">Y coordinate</item>
            <item name="NickName" type_name="gh_string" type_code="10">Y</item>
            <item name="Optional" type_name="gh_bool" type_code="1">false</item>
            <item name="Source" index="0" type_name="gh_guid" type_code="9">84845043-6f2a-4df0-927f-257b8a167cfe</item>
            <item name="SourceCount" type_name="gh_int32" type_code="3">1</item>
          </items>
          <chunks count="2">
            <chunk name="Attributes">
              <items count="2">
                <item name="Bounds" type_name="gh_drawing_rectanglef" type_code="35">
                  <X>12915</X>
                  <Y>3992</Y>
                  <W>14</W>
                  <H>20</H>
                </item>
                <item name="Pivot" type_name="gh_drawing_pointf" type_code="31">
                  <X>12923.5</X>
                  <Y>4002</Y>
                </item>
              </items>
            </chunk>
            <chunk name="PersistentData">
              <items count="1">
                <item name="Count" type_name="gh_int32" type_code="3">1</item>
              </items>
              <chunks count="1">
                <chunk name="Branch" index="0">
                  <items count="2">
                    <item name="Count" type_name="gh_int32" type_code="3">1</item>
                    <item name="Path" type_name="gh_string" type_code="10">{0}</item>
                  </items>
                  <chunks count="1">
                    <chunk name="Item" index="0">
                      <items count="1">
                        <item name="number" type_name="gh_double" type_code="6">20</item>
                      </items>
                    </chunk>
                  </chunks>
                </chunk>
              </chunks>
            </chunk>
          </chunks>
        </chunk>
        <chunk name="param_input" index="2">
          <items count="6">
            <item name="Description" type_name="gh_string" type_code="10">{z} coordinate</item>
            <item name="InstanceGuid" type_name="gh_guid" type_code="9">c8021107-b439-4d82-9d0c-854f10475997</item>
            <item name="Name" type_name="gh_string" type_code="10">Z coordinate</item>
            <item name="NickName" type_name="gh_string" type_code="10">Z</item>
            <item name="Optional" type_name="gh_bool" type_code="1">false</item>
            <item name="SourceCount" type_name="gh_int32" type_code="3">0</item>
          </items>
          <chunks count="2">
            <chunk name="Attributes">
              <items count="2">
                <item name="Bounds" type_name="gh_drawing_rectanglef" type_code="35">
                  <X>12915</X>
                  <Y>4012</Y>
                  <W>14</W>
                  <H>20</H>
                </item>
                <item name="Pivot" type_name="gh_drawing_pointf" type_code="31">
                  <X>12923.5</X>
                  <Y>4022</Y>
                </item>
              </items>
            </chunk>
            <chunk name="PersistentData">
              <items count="1">
                <item name="Count" type_name="gh_int32" type_code="3">1</item>
              </items>
              <chunks count="1">
                <chunk name="Branch" index="0">
                  <items count="2">
                    <item name="Count" type_name="gh_int32" type_code="3">1</item>
                    <item name="Path" type_name="gh_string" type_code="10">{0}</item>
                  </items>
                  <chunks count="1">
                    <chunk name="Item" index="0">
                      <items count="1">
                        <item name="number" type_name="gh_double" type_code="6">0</item>
                      </items>
                    </chunk>
                  </chunks>
                </chunk>
              </chunks>
            </chunk>
          </chunks>
        </chunk>
        <chunk name="param_output" index="0">
          <items count="6">
            <item name="Description" type_name="gh_string" type_code="10">Point coordinate</item>
            <item name="InstanceGuid" type_name="gh_guid" type_code="9">b897a70c-27b4-4d8a-9d42-d335c88dbf7c</item>
            <item name="Name" type_name="gh_string" type_code="10">Point</item>
            <item name="NickName" type_name="gh_string" type_code="10">Pt</item>
            <item name="Optional" type_name="gh_bool" type_code="1">false</item>
            <item name="SourceCount" type_name="gh_int32" type_code="3">0</item>
          </items>
          <chunks count="1">
            <chunk name="Attributes">
              <items count="2">
                <item name="Bounds" type_name="gh_drawing_rectanglef" type_code="35">
                  <X>12959</X>
                  <Y>3972</Y>
                  <W>20</W>
                  <H>60</H>
                </item>
                <item name="Pivot" type_name="gh_drawing_pointf" type_code="31">
                  <X>12969</X>
                  <Y>4002</Y>
                </item>
              </items>
            </chunk>
          </chunks>
        </chunk>
      </chunks>
    </chunk>
  </chunks>
</chunk>